{
	"events": [
		{
			"character": "character-1641620862.json",
			"event_id": "dialogic_010",
			"options": [

			],
			"portrait": "",
			"question": "So..."
		},
		{
			"choice": "What do you remember from last night?",
			"condition": "",
			"definition": "",
			"event_id": "dialogic_011",
			"value": ""
		},
		{
			"definition": "1641699745-787",
			"event_id": "dialogic_014",
			"operation": "=",
			"random_upper_limit": 100,
			"set_random": false,
			"set_value": "1"
		},
		{
			"definition": "1641699607-648",
			"event_id": "dialogic_014",
			"operation": "-",
			"random_upper_limit": 100,
			"set_random": false,
			"set_value": "1"
		},
		{
			"definition": "1641699607-648",
			"event_id": "dialogic_014",
			"operation": "+",
			"random_upper_limit": 100,
			"set_random": false,
			"set_value": "1"
		},
		{
			"character": "character-1641620862.json",
			"event_id": "dialogic_001",
			"portrait": "",
			"text": "What do you remember from last night, Henry?"
		},
		{
			"character": "character-1641699170.json",
			"event_id": "dialogic_001",
			"portrait": "",
			"text": "Well, like I said, I was recording an episode of my cooking show. And I was..."
		},
		{
			"character": "character-1641620862.json",
			"event_id": "dialogic_001",
			"portrait": "",
			"text": "Cooking."
		},
		{
			"character": "character-1641699170.json",
			"event_id": "dialogic_001",
			"portrait": "",
			"text": "Yeah. For the show."
		},
		{
			"character": "character-1641665865.json",
			"event_id": "dialogic_001",
			"portrait": "",
			"text": "Asking this man questions was like pulling goddamn teeth."
		},
		{
			"condition": "",
			"definition": "1641699754-366",
			"event_id": "dialogic_012",
			"value": "0"
		},
		{
			"definition": "1641700484-918",
			"event_id": "dialogic_014",
			"operation": "=",
			"random_upper_limit": 100,
			"set_random": false,
			"set_value": "1"
		},
		{
			"character": "character-1641620862.json",
			"event_id": "dialogic_001",
			"portrait": "",
			"text": "And Mr. Thoroughbred just let you do that while you're on the clock? Awfully generous of him."
		},
		{
			"character": "character-1641699170.json",
			"event_id": "dialogic_001",
			"portrait": "",
			"text": "He'd already eaten dinner."
		},
		{
			"character": "character-1641620862.json",
			"event_id": "dialogic_001",
			"portrait": "",
			"text": "So you were cooking again."
		},
		{
			"character": "character-1641699170.json",
			"event_id": "dialogic_001",
			"portrait": "",
			"text": "Again? No, no, he didn't eat my food."
		},
		{
			"character": "character-1641620862.json",
			"event_id": "dialogic_001",
			"portrait": "",
			"text": "Last night?"
		},
		{
			"character": "character-1641699170.json",
			"event_id": "dialogic_001",
			"portrait": "",
			"text": "..."
		},
		{
			"character": "character-1641665865.json",
			"event_id": "dialogic_001",
			"portrait": "",
			"text": "The man finally showed an emotion besides hollow-eyed horror at his own existence. Guilt. Something I could push."
		},
		{
			"character": "character-1641620862.json",
			"event_id": "dialogic_001",
			"portrait": "",
			"text": "Henry, I asked you a question."
		},
		{
			"character": "character-1641699170.json",
			"event_id": "dialogic_001",
			"portrait": "",
			"text": "Ever."
		},
		{
			"character": "character-1641620862.json",
			"event_id": "dialogic_001",
			"portrait": "",
			"text": "What?"
		},
		{
			"character": "character-1641699170.json",
			"event_id": "dialogic_001",
			"portrait": "",
			"text": "Ever. He didn't ever eat my cooking."
		},
		{
			"character": "character-1641620862.json",
			"event_id": "dialogic_001",
			"portrait": "",
			"text": "You're a cook, and the man never ate your cooking."
		},
		{
			"character": "character-1641699170.json",
			"event_id": "dialogic_001",
			"portrait": "",
			"text": "Right. He said it was a joke. Like my life."
		},
		{
			"character": "character-1641665865.json",
			"event_id": "dialogic_001",
			"portrait": "",
			"text": "Holy shit."
		},
		{
			"character": "character-1641620862.json",
			"event_id": "dialogic_001",
			"portrait": "",
			"text": "You work for a man who trashes you like that?"
		},
		{
			"character": "character-1641699170.json",
			"event_id": "dialogic_001",
			"portrait": "",
			"text": "No, he didn't say that. My life IS a joke."
		},
		{
			"character": "character-1641665865.json",
			"event_id": "dialogic_001",
			"portrait": "",
			"text": "I wanted to ask more about the sick comedy this man had turned into, but I just couldn't get myself to do it. Life had come to kick this guy while he was down and found him kicking himself."
		},
		{
			"character": "character-1641620862.json",
			"event_id": "dialogic_001",
			"portrait": "",
			"text": "Fine, fine."
		},
		{
			"event_id": "dialogic_013"
		},
		{
			"condition": "",
			"definition": "1641699754-366",
			"event_id": "dialogic_012",
			"value": "1"
		},
		{
			"character": "",
			"event_id": "dialogic_001",
			"portrait": "",
			"text": "Well, I know you weren't cooking for Mr. Thoroughbred, since he didn't eat your food. Pretty cushy job, getting paid to do work you were going to do anyway. "
		},
		{
			"event_id": "dialogic_013"
		},
		{
			"character": "character-1641620862.json",
			"event_id": "dialogic_010",
			"options": [

			],
			"portrait": "",
			"question": "So you recorded the cooking show."
		},
		{
			"choice": "Did anything suspicious happen while you were recording?",
			"condition": "",
			"definition": "",
			"event_id": "dialogic_011",
			"value": ""
		},
		{
			"character": "character-1641620862.json",
			"event_id": "dialogic_001",
			"portrait": "",
			"text": "Did you notice anything while recording?"
		},
		{
			"character": "character-1641699170.json",
			"event_id": "dialogic_001",
			"portrait": "",
			"text": "No. Just the cooking. You have to pay a lot of attention while you're cooking or else you can just kind of... fuck it all up."
		},
		{
			"character": "character-1641665865.json",
			"event_id": "dialogic_001",
			"portrait": "",
			"text": "I took a look at the mess he called a kitchen."
		},
		{
			"character": "character-1641620862.json",
			"event_id": "dialogic_001",
			"portrait": "",
			"text": "Point taken. Still though, nothing at all? No sounds, no anything?"
		},
		{
			"character": "character-1641699170.json",
			"event_id": "dialogic_001",
			"portrait": "",
			"text": "Well, Mr. Thoroughbred had a visitor earlier in the night. He asked me to get him something, but I told him I was busy. Then he called me a \"pussa bitch\"."
		},
		{
			"character": "character-1641620862.json",
			"event_id": "dialogic_001",
			"portrait": "",
			"text": "A visitor? Sounds like something pretty important to leave out for a murder investigation, Henry."
		},
		{
			"character": "character-1641699170.json",
			"event_id": "dialogic_001",
			"portrait": "",
			"text": "Like I said, I was busy. I didn't see the guy."
		},
		{
			"character": "character-1641620862.json",
			"event_id": "dialogic_001",
			"portrait": "",
			"text": "When did he leave?"
		},
		{
			"character": "character-1641699170.json",
			"event_id": "dialogic_001",
			"portrait": "",
			"text": "I don't know."
		},
		{
			"character": "character-1641620862.json",
			"event_id": "dialogic_001",
			"portrait": "",
			"text": "So this guy could be our perp, is what you're saying? Somebody you didn't see come in, and didn't hear leave."
		},
		{
			"character": "character-1641699170.json",
			"event_id": "dialogic_001",
			"portrait": "",
			"text": "..."
		},
		{
			"character": "character-1641620862.json",
			"event_id": "dialogic_001",
			"portrait": "",
			"text": "Never mind. We can worry about that later."
		},
		{
			"choice": "Can I see the episode?",
			"condition": "",
			"definition": "",
			"event_id": "dialogic_011",
			"value": ""
		},
		{
			"character": "character-1641665865.json",
			"event_id": "dialogic_001",
			"portrait": "",
			"text": "Might be something worth seeing in that footage. Henry seemed a few watts short of a working bulb, but the camera wouldn't miss a thing. Assuming he remembered to turn it on."
		},
		{
			"character": "character-1641620862.json",
			"event_id": "dialogic_001",
			"portrait": "",
			"text": "Can I see the episode you recorded? There might be some hints, something happening in the background that you missed."
		},
		{
			"character": "character-1641699170.json",
			"event_id": "dialogic_001",
			"portrait": "",
			"text": "No. It's not edited yet."
		},
		{
			"character": "character-1641620862.json",
			"event_id": "dialogic_001",
			"portrait": "",
			"text": "Henry, this is a police investigation. You might have evidence in there."
		},
		{
			"character": "character-1641665865.json",
			"event_id": "dialogic_001",
			"portrait": "",
			"text": "Something I'd damn sure like to know about."
		},
		{
			"character": "character-1641699170.json",
			"event_id": "dialogic_001",
			"portrait": "",
			"text": "No."
		},
		{
			"character": "character-1641620862.json",
			"event_id": "dialogic_001",
			"portrait": "",
			"text": "Why not, Henry? Something in there you don't want us to see?"
		},
		{
			"character": "character-1641699170.json",
			"event_id": "dialogic_001",
			"portrait": "",
			"text": "It's seven hours long."
		},
		{
			"character": "character-1641620862.json",
			"event_id": "dialogic_001",
			"portrait": "",
			"text": "..."
		},
		{
			"character": "character-1641699170.json",
			"event_id": "dialogic_001",
			"portrait": "",
			"text": "There were some... mistakes. So I have to go edit it."
		},
		{
			"character": "character-1641620862.json",
			"event_id": "dialogic_001",
			"portrait": "",
			"text": "Yeah. Maybe forensics can help you do it."
		},
		{
			"character": "character-1641699170.json",
			"event_id": "dialogic_001",
			"portrait": "",
			"text": "Well, they'll have to get it off my laptop first."
		},
		{
			"character": "character-1641665865.json",
			"event_id": "dialogic_001",
			"portrait": "",
			"text": "It was on his laptop? Good to know."
		},
		{
			"event_id": "dialogic_013"
		},
		{
			"custom_slot": "",
			"event_id": "dialogic_026",
			"use_default_slot": true
		},
		{
			"change_timeline": "timeline-1641700947.json",
			"event_id": "dialogic_020"
		},
		{
			"choice": "How'd you become a cook for Mr. Thoroughbred?",
			"condition": "",
			"definition": "",
			"event_id": "dialogic_011",
			"value": ""
		},
		{
			"definition": "1641699754-366",
			"event_id": "dialogic_014",
			"operation": "=",
			"random_upper_limit": 100,
			"set_random": false,
			"set_value": "1"
		},
		{
			"definition": "1641699607-648",
			"event_id": "dialogic_014",
			"operation": "-",
			"random_upper_limit": 100,
			"set_random": false,
			"set_value": "1"
		},
		{
			"definition": "1641699607-648",
			"event_id": "dialogic_014",
			"operation": "+",
			"random_upper_limit": 100,
			"set_random": false,
			"set_value": "1"
		},
		{
			"character": "character-1641620862.json",
			"event_id": "dialogic_001",
			"portrait": "",
			"text": "So how did you become a cook for Mr. Thoroughbred, Henry?"
		},
		{
			"character": "character-1641699170.json",
			"event_id": "dialogic_001",
			"portrait": "",
			"text": "He messaged me online and said he liked my videos, and told me he'd like to get a taste of Henry's Famous Cooking himself. I thought I could make a video about it. He offered to fly me out to Las Borpas, even."
		},
		{
			"condition": "",
			"definition": "1641700484-918",
			"event_id": "dialogic_012",
			"value": "1"
		},
		{
			"character": "character-1641620862.json",
			"event_id": "dialogic_001",
			"portrait": "",
			"text": "Well, I think we know how that went."
		},
		{
			"character": "character-1641699170.json",
			"event_id": "dialogic_001",
			"portrait": "",
			"text": "Yeah. He kind of spat the food out and said \"this tastes like hot garbage, dawg.\""
		},
		{
			"character": "character-1641620862.json",
			"event_id": "dialogic_001",
			"portrait": "",
			"text": "Wait a minute... if he hated your food so much, why did he keep you? "
		},
		{
			"character": "character-1641699170.json",
			"event_id": "dialogic_001",
			"portrait": "",
			"text": "He said it was just as dogshit as he expected."
		},
		{
			"event_id": "dialogic_013"
		},
		{
			"condition": "",
			"definition": "1641700484-918",
			"event_id": "dialogic_012",
			"value": "0"
		},
		{
			"character": "character-1641620862.json",
			"event_id": "dialogic_001",
			"portrait": "",
			"text": "Yeah? And how did that go?"
		},
		{
			"character": "character-1641699170.json",
			"event_id": "dialogic_001",
			"portrait": "",
			"text": "It... wasn't his favorite."
		},
		{
			"character": "character-1641620862.json",
			"event_id": "dialogic_001",
			"portrait": "",
			"text": "Can you be more specific?"
		},
		{
			"character": "character-1641699170.json",
			"event_id": "dialogic_001",
			"portrait": "",
			"text": "He spat it out."
		},
		{
			"character": "character-1641620862.json",
			"event_id": "dialogic_001",
			"portrait": "",
			"text": "..."
		},
		{
			"character": "character-1641699170.json",
			"event_id": "dialogic_001",
			"portrait": "",
			"text": "Then he called it \"hot garbage, dawg.\""
		},
		{
			"character": "character-1641620862.json",
			"event_id": "dialogic_001",
			"portrait": "",
			"text": "..."
		},
		{
			"character": "character-1641699170.json",
			"event_id": "dialogic_001",
			"portrait": "",
			"text": "\"Literally fucking inedible, my guy.\""
		},
		{
			"character": "character-1641620862.json",
			"event_id": "dialogic_001",
			"portrait": "",
			"text": "Wow."
		},
		{
			"character": "character-1641699170.json",
			"event_id": "dialogic_001",
			"portrait": "",
			"text": "\"Just as dogshit as I expected.\""
		},
		{
			"character": "character-1641620862.json",
			"event_id": "dialogic_001",
			"portrait": "",
			"text": "Stop."
		},
		{
			"event_id": "dialogic_013"
		},
		{
			"character": "character-1641620862.json",
			"event_id": "dialogic_001",
			"portrait": "",
			"text": "So he kept you around as a joke?"
		},
		{
			"character": "character-1641699170.json",
			"event_id": "dialogic_001",
			"portrait": "",
			"text": "More or less. And I got to keep making videos, so it's like I had two jobs, but I only had to do one. Which.... I guess I only have one job now..."
		},
		{
			"character": "character-1641665865.json",
			"event_id": "dialogic_001",
			"portrait": "",
			"text": "He lapsed back into a thousand yard stare, like he was trying to see through the walls of the estate and down the long dark tunnel of his life still to come, praying for an oncoming train."
		},
		{
			"character": "character-1641620862.json",
			"event_id": "dialogic_001",
			"portrait": "",
			"text": "That's Las Borpas for you Henry. It'll chew you up and spit you out like your own goddamn cooking."
		},
		{
			"custom_slot": "",
			"event_id": "dialogic_026",
			"use_default_slot": true
		},
		{
			"change_timeline": "timeline-1641700947.json",
			"event_id": "dialogic_020"
		},
		{
			"choice": "Got any spring rolls?",
			"condition": "",
			"definition": "",
			"event_id": "dialogic_011",
			"value": ""
		},
		{
			"definition": "1641699769-146",
			"event_id": "dialogic_014",
			"operation": "=",
			"random_upper_limit": 100,
			"set_random": false,
			"set_value": "1"
		},
		{
			"character": "character-1641620862.json",
			"event_id": "dialogic_001",
			"portrait": "",
			"text": "I heard you had some spring rolls around, and I haven't eaten yet. Mind if I have some?"
		},
		{
			"character": "character-1641699170.json",
			"event_id": "dialogic_001",
			"portrait": "",
			"text": "Really? You want one?"
		},
		{
			"character": "character-1641620862.json",
			"event_id": "dialogic_001",
			"portrait": "",
			"text": "No."
		},
		{
			"custom_slot": "",
			"event_id": "dialogic_026",
			"use_default_slot": true
		},
		{
			"change_timeline": "timeline-1641700947.json",
			"event_id": "dialogic_020"
		},
		{
			"choice": "I'm done.",
			"condition": ">=",
			"definition": "1641699607-648",
			"event_id": "dialogic_011",
			"value": "1"
		},
		{
			"character": "character-1641620862.json",
			"event_id": "dialogic_001",
			"portrait": "",
			"text": "Think I'm all done here, Henry."
		},
		{
			"character": "character-1641699170.json",
			"event_id": "dialogic_001",
			"portrait": "",
			"text": "Hey, do you think you can like and subscribe to..."
		},
		{
			"character": "character-1641620862.json",
			"event_id": "dialogic_001",
			"portrait": "",
			"text": "Absolutely not. Just like that, I was out of that kitchen like Henry out of a job."
		},
		{
			"event_id": "dialogic_013"
		},
		{
			"custom_slot": "",
			"event_id": "dialogic_026",
			"use_default_slot": true
		}
	],
	"metadata": {
		"dialogic-version": "1.3",
		"file": "timeline-1641700947.json",
		"name": "kitchen-1-questions"
	}
}
